README.md
setup.py
simple_measuretime/__init__.py
simple_measuretime/simple_measuretime.py
simple_measuretime.egg-info/PKG-INFO
simple_measuretime.egg-info/SOURCES.txt
simple_measuretime.egg-info/dependency_links.txt
simple_measuretime.egg-info/top_level.txt