Metadata-Version: 2.1
Name: simple-measuretime
Version: 1.0.3
Summary: This is a simple package to measure the time in Python.
Author: seyuriti
Author-email: aesioseyuri@gmail.com
Classifier: Programming Language :: Python :: 3
Classifier: License :: OSI Approved :: MIT License
Classifier: Operating System :: OS Independent
Requires-Python: >=3.6
